pytextalterations/__init__.py
pytextalterations/__main__.py
pytextalterations/capitalize_sentences.py
pytextalterations/most_frequent_words.py
pytextalterations/remove.py
pytextalterations/sentence_count.py
pytextalterations-1.1.0.dist-info/LICENSE
pytextalterations-1.1.0.dist-info/METADATA
pytextalterations-1.1.0.dist-info/WHEEL
pytextalterations-1.1.0.dist-info/top_level.txt
pytextalterations-1.1.0.dist-info/RECORD
