Metadata-Version: 2.1
Name: pytextalterations
Version: 1.1.0
Summary: A package that alters text in four different ways.
Author-email: Neha Magesh <nm3818@nyu.edu>, Luca Ignatescu <lucaignatescu003@gmail.com>, James Whitten <jjw9064@nyu.edu>, Tahsin Tawhid <tt2248@nyu.edu>
License: GNU GENERAL PUBLIC LICENSE
Project-URL: Homepage, https://github.com/software-students-fall2024/3-python-package-subwaysurfers
Project-URL: Repository, https://github.com/software-students-fall2024/3-python-package-subwaysurfers.git
Project-URL: Bug Tracker, https://github.com/software-students-fall2024/3-python-package-subwaysurfers/issues
Keywords: python,package,build,tutorial
Classifier: Programming Language :: Python :: 3
Classifier: Intended Audience :: Education
Classifier: License :: OSI Approved :: GNU General Public License v3 (GPLv3)
Classifier: Operating System :: OS Independent
Requires-Python: >=3.7
License-File: LICENSE
Requires-Dist: regex
Provides-Extra: dev
Requires-Dist: pytest; extra == "dev"
Requires-Dist: build; extra == "dev"
Requires-Dist: twine; extra == "dev"
